README
setup.py
omt/__init__.py
omt/cli.py
omt/core.py
omt/util.py
omt.egg-info/PKG-INFO
omt.egg-info/SOURCES.txt
omt.egg-info/dependency_links.txt
omt.egg-info/entry_points.txt
omt.egg-info/requires.txt
omt.egg-info/top_level.txt