Metadata-Version: 1.0
Name: omt
Version: 0.1.0
Summary: Tools for turning terminal sessions into JSON/HTML.
Home-page: http://github.com/tktech/omt
Author: Tyler Kennedy
Author-email: tk@tkte.ch
License: UNKNOWN
Platform: UNKNOWN
